wyqpy/__init__.py
wyqpy/base/__init__.py
wyqpy/base/datetime.py
wyqpy/base/path.py
wyqpy/base/platform.py
wyqpy/io/__init__.py
wyqpy/io/directory.py
wyqpy/io/file.py
wyqpy/math/__init__.py
wyqpy/math/prime.py
wyqpy/net/__init__.py
wyqpy/office/__init__.py
wyqpy/ui/__init__.py
wyqpy-0.1.3.3.dist-info/METADATA
wyqpy-0.1.3.3.dist-info/WHEEL
wyqpy-0.1.3.3.dist-info/top_level.txt
wyqpy-0.1.3.3.dist-info/RECORD
