Metadata-Version: 2.1
Name: wyqpy
Version: 0.1.3.3
Summary: The WYQ CPython Functions
Home-page: http://www.wylib.com/py/lib/
Author: WYQ
Author-email: wyqlib@qq.com
Maintainer: WYQ
Maintainer-email: wyqlib@qq.com
License: MIT
Download-URL: http://www.wyqlib.com/py/lib
Keywords: tool utils lib
Platform: UNKNOWN
Requires-Python: >=3.6
Requires-Dist: python-docx
Requires-Dist: openpyxl
Requires-Dist: xlsxwriter
Requires-Dist: xlrd
Requires-Dist: xlwt
Requires-Dist: xlutils
Requires-Dist: html5lib
Requires-Dist: lxml
Requires-Dist: beautifulsoup4
